setup.py
../../version.ini
grr_response_client_builder/__init__.py
grr_response_client_builder/build.py
grr_response_client_builder/build_helpers.py
grr_response_client_builder/build_helpers_test.py
grr_response_client_builder/client_build.py
grr_response_client_builder/client_build_test.py
grr_response_client_builder/distro_entry.py
grr_response_client_builder/fake_fleetspeak_windows_service.py
grr_response_client_builder/pkg_utils.py
grr_response_client_builder/pkg_utils_test.py
grr_response_client_builder/repacking.py
grr_response_client_builder/repacking_test.py
grr_response_client_builder/signing.py
grr_response_client_builder/signing_test.py
grr_response_client_builder/windows_msi_test.py
grr_response_client_builder.egg-info/PKG-INFO
grr_response_client_builder.egg-info/SOURCES.txt
grr_response_client_builder.egg-info/dependency_links.txt
grr_response_client_builder.egg-info/entry_points.txt
grr_response_client_builder.egg-info/requires.txt
grr_response_client_builder.egg-info/top_level.txt
grr_response_client_builder/builders/__init__.py
grr_response_client_builder/builders/linux.py
grr_response_client_builder/builders/osx.py
grr_response_client_builder/builders/windows.py
grr_response_client_builder/repackers/__init__.py
grr_response_client_builder/repackers/cab_utils.py
grr_response_client_builder/repackers/cab_utils_test.py
grr_response_client_builder/repackers/linux.py
grr_response_client_builder/repackers/osx.py
grr_response_client_builder/repackers/windows.py