Metadata-Version: 2.4
Name: grr-response-client-builder
Version: 4.0.0.post0
Summary: GRR Rapid Response
Home-page: https://github.com/google/grr
Maintainer: GRR Development Team
Maintainer-email: grr-dev@googlegroups.com
License: Apache License, Version 2.0
Requires-Python: >=3.9
Requires-Dist: distro==1.7.0
Requires-Dist: grr-response-client==4.0.0post0
Requires-Dist: grr-response-core==4.0.0post0
Requires-Dist: fleetspeak-client-bin==0.1.13
Requires-Dist: olefile==0.46
Requires-Dist: PyInstaller==5.13.2
Dynamic: home-page
Dynamic: license
Dynamic: maintainer
Dynamic: maintainer-email
Dynamic: requires-dist
Dynamic: requires-python
Dynamic: summary
